m2cgen/VERSION.txt
m2cgen/__init__.py
m2cgen/__main__.py
m2cgen/ast.py
m2cgen/cli.py
m2cgen/exporters.py
m2cgen/assemblers/__init__.py
m2cgen/assemblers/base.py
m2cgen/assemblers/boosting.py
m2cgen/assemblers/ensemble.py
m2cgen/assemblers/fallback_expressions.py
m2cgen/assemblers/linear.py
m2cgen/assemblers/meta.py
m2cgen/assemblers/svm.py
m2cgen/assemblers/tree.py
m2cgen/assemblers/utils.py
m2cgen/interpreters/__init__.py
m2cgen/interpreters/code_generator.py
m2cgen/interpreters/interpreter.py
m2cgen/interpreters/mixins.py
m2cgen/interpreters/utils.py
m2cgen/interpreters/c/__init__.py
m2cgen/interpreters/c/code_generator.py
m2cgen/interpreters/c/interpreter.py
m2cgen/interpreters/c/linear_algebra.c
m2cgen/interpreters/c/sigmoid.c
m2cgen/interpreters/c/softmax.c
m2cgen/interpreters/c_sharp/__init__.py
m2cgen/interpreters/c_sharp/code_generator.py
m2cgen/interpreters/c_sharp/interpreter.py
m2cgen/interpreters/c_sharp/linear_algebra.cs
m2cgen/interpreters/c_sharp/log1p.cs
m2cgen/interpreters/c_sharp/sigmoid.cs
m2cgen/interpreters/c_sharp/softmax.cs
m2cgen/interpreters/dart/__init__.py
m2cgen/interpreters/dart/code_generator.py
m2cgen/interpreters/dart/interpreter.py
m2cgen/interpreters/dart/linear_algebra.dart
m2cgen/interpreters/dart/log1p.dart
m2cgen/interpreters/dart/sigmoid.dart
m2cgen/interpreters/dart/softmax.dart
m2cgen/interpreters/dart/tanh.dart
m2cgen/interpreters/elixir/__init__.py
m2cgen/interpreters/elixir/code_generator.py
m2cgen/interpreters/elixir/interpreter.py
m2cgen/interpreters/elixir/linear_algebra.ex
m2cgen/interpreters/elixir/log1p.ex
m2cgen/interpreters/elixir/sigmoid.ex
m2cgen/interpreters/elixir/softmax.ex
m2cgen/interpreters/f_sharp/__init__.py
m2cgen/interpreters/f_sharp/code_generator.py
m2cgen/interpreters/f_sharp/interpreter.py
m2cgen/interpreters/f_sharp/linear_algebra.fs
m2cgen/interpreters/f_sharp/log1p.fs
m2cgen/interpreters/f_sharp/sigmoid.fs
m2cgen/interpreters/f_sharp/softmax.fs
m2cgen/interpreters/go/__init__.py
m2cgen-0.10.0.dist-info/LICENSE
m2cgen-0.10.0.dist-info/METADATA
m2cgen-0.10.0.dist-info/WHEEL
m2cgen-0.10.0.dist-info/entry_points.txt
m2cgen-0.10.0.dist-info/top_level.txt
m2cgen-0.10.0.dist-info/RECORD
